Pokebola/__init__.py
Pokebola/pokemon.csv
Pokebola/random_pokemon.py
Pokebola-1.0.4.dist-info/METADATA
Pokebola-1.0.4.dist-info/WHEEL
Pokebola-1.0.4.dist-info/top_level.txt
Pokebola-1.0.4.dist-info/RECORD
