Metadata-Version: 2.1
Name: Pokebola
Version: 1.0.4
Summary: Libreria para generar un Pokemon aleatorio
Author: Rogelio Guzman
Author-email: miniroyerguzman@gmail.com
Requires-Dist: pandas
